<?xml version="1.0" encoding="utf-8"?>
<edmx:Edmx Version="4.0" xmlns:edmx="http://docs.oasis-open.org/odata/ns/edmx" xmlns="http://docs.oasis-open.org/odata/ns/edm">
    <edmx:Reference Uri="/sap/opu/odata/IWFND/CATALOGSERVICE;v=2/Vocabularies(TechnicalName='%2FIWBEP%2FVOC_COMMUNICATION',Version='0001',SAP__Origin='LOCAL')/$value">
        <edmx:Include Namespace="com.sap.vocabularies.Communication.v1" Alias="Communication"/>
    </edmx:Reference>
    <edmx:Reference Uri="/sap/opu/odata/IWFND/CATALOGSERVICE;v=2/Vocabularies(TechnicalName='%2FIWBEP%2FVOC_PERSONALDATA',Version='0001',SAP__Origin='LOCAL')/$value">
        <edmx:Include Namespace="com.sap.vocabularies.PersonalData.v1" Alias="PersonalData"/>
    </edmx:Reference>
    <edmx:Reference Uri="/sap/opu/odata/IWFND/CATALOGSERVICE;v=2/Vocabularies(TechnicalName='%2FIWBEP%2FVOC_ANALYTICS',Version='0001',SAP__Origin='LOCAL')/$value">
        <edmx:Include Namespace="com.sap.vocabularies.Analytics.v1" Alias="Analytics"/>
    </edmx:Reference>
    <edmx:Reference Uri="/sap/opu/odata/IWFND/CATALOGSERVICE;v=2/Vocabularies(TechnicalName='%2FIWBEP%2FVOC_COMMON',Version='0001',SAP__Origin='LOCAL')/$value">
        <edmx:Include Namespace="com.sap.vocabularies.Common.v1" Alias="SAP__common"/>
    </edmx:Reference>
    <edmx:Reference Uri="/sap/opu/odata/IWFND/CATALOGSERVICE;v=2/Vocabularies(TechnicalName='%2FIWBEP%2FVOC_MEASURES',Version='0001',SAP__Origin='LOCAL')/$value">
        <edmx:Include Namespace="Org.OData.Measures.V1" Alias="SAP__measures"/>
    </edmx:Reference>
    <edmx:Reference Uri="/sap/opu/odata/IWFND/CATALOGSERVICE;v=2/Vocabularies(TechnicalName='%2FIWBEP%2FVOC_CORE',Version='0001',SAP__Origin='LOCAL')/$value">
        <edmx:Include Namespace="Org.OData.Core.V1" Alias="SAP__core"/>
    </edmx:Reference>
    <edmx:Reference Uri="/sap/opu/odata/IWFND/CATALOGSERVICE;v=2/Vocabularies(TechnicalName='%2FIWBEP%2FVOC_CAPABILITIES',Version='0001',SAP__Origin='LOCAL')/$value">
        <edmx:Include Namespace="Org.OData.Capabilities.V1" Alias="SAP__capabilities"/>
    </edmx:Reference>
    <edmx:Reference Uri="/sap/opu/odata/IWFND/CATALOGSERVICE;v=2/Vocabularies(TechnicalName='%2FIWBEP%2FVOC_AGGREGATION',Version='0001',SAP__Origin='LOCAL')/$value">
        <edmx:Include Namespace="Org.OData.Aggregation.V1" Alias="SAP__aggregation"/>
    </edmx:Reference>
    <edmx:Reference Uri="/sap/opu/odata/IWFND/CATALOGSERVICE;v=2/Vocabularies(TechnicalName='%2FIWBEP%2FVOC_VALIDATION',Version='0001',SAP__Origin='LOCAL')/$value">
        <edmx:Include Namespace="Org.OData.Validation.V1" Alias="SAP__validation"/>
    </edmx:Reference>
    <edmx:Reference Uri="/sap/opu/odata/IWFND/CATALOGSERVICE;v=2/Vocabularies(TechnicalName='%2FIWBEP%2FVOC_CODELIST',Version='0001',SAP__Origin='LOCAL')/$value">
        <edmx:Include Namespace="com.sap.vocabularies.CodeList.v1" Alias="SAP__CodeList"/>
    </edmx:Reference>
    <edmx:Reference Uri="/sap/opu/odata/IWFND/CATALOGSERVICE;v=2/Vocabularies(TechnicalName='%2FIWBEP%2FVOC_UI',Version='0001',SAP__Origin='LOCAL')/$value">
        <edmx:Include Namespace="com.sap.vocabularies.UI.v1" Alias="SAP__UI"/>
    </edmx:Reference>
    <edmx:Reference Uri="/sap/opu/odata/IWFND/CATALOGSERVICE;v=2/Vocabularies(TechnicalName='%2FIWBEP%2FVOC_HTML5',Version='0001',SAP__Origin='LOCAL')/$value">
        <edmx:Include Namespace="com.sap.vocabularies.HTML5.v1" Alias="SAP__HTML5"/>
    </edmx:Reference>
    <edmx:Reference Uri="/sap/opu/odata/IWFND/CATALOGSERVICE;v=2/Vocabularies(TechnicalName='%2FIWBEP%2FVOC_PDF',Version='0001',SAP__Origin='LOCAL')/$value">
        <edmx:Include Namespace="com.sap.vocabularies.PDF.v1" Alias="SAP__PDF"/>
    </edmx:Reference>
    <edmx:Reference Uri="/sap/opu/odata/IWFND/CATALOGSERVICE;v=2/Vocabularies(TechnicalName='%2FIWBEP%2FVOC_SESSION',Version='0001',SAP__Origin='LOCAL')/$value">
        <edmx:Include Namespace="com.sap.vocabularies.Session.v1" Alias="SAP__session"/>
    </edmx:Reference>
    <edmx:Reference Uri="/sap/opu/odata/IWFND/CATALOGSERVICE;v=2/Vocabularies(TechnicalName='%2FIWBEP%2FVOC_ODM',Version='0001',SAP__Origin='LOCAL')/$value">
        <edmx:Include Namespace="com.sap.vocabularies.ODM.v1" Alias="SAP__ODM"/>
    </edmx:Reference>
    <edmx:Reference Uri="/sap/opu/odata/IWFND/CATALOGSERVICE;v=2/Vocabularies(TechnicalName='%2FIWBEP%2FVOC_HIERARCHY',Version='0001',SAP__Origin='LOCAL')/$value">
        <edmx:Include Namespace="com.sap.vocabularies.Hierarchy.v1" Alias="SAP__hierarchy"/>
    </edmx:Reference>
    <edmx:DataServices>
        <Schema Namespace="com.sap.gateway.srvd.zui_daystocktrans_o4.v0001" Alias="SAP__self">
            <Annotation Term="SAP__core.SchemaVersion" String="1.0.0"/>
            <EntityType Name="ZC_DAYSTOCKTRANSType">
                <Key>
                    <PropertyRef Name="ExcuDate"/>
                    <PropertyRef Name="Companycode"/>
                    <PropertyRef Name="Plant"/>
                    <PropertyRef Name="BusinessPartner"/>
                </Key>
                <Property Name="ExcuDate" Type="Edm.Date" Nullable="false"/>
                <Property Name="Companycode" Type="Edm.String" Nullable="false" MaxLength="4"/>
                <Property Name="Plant" Type="Edm.String" Nullable="false" MaxLength="4"/>
                <Property Name="BusinessPartner" Type="Edm.String" Nullable="false" MaxLength="10"/>
                <Property Name="BusinessPartnerName" Type="Edm.String" Nullable="false" MaxLength="81"/>
                <Property Name="ProductPrice" Type="Edm.Decimal" Nullable="false" Precision="15" Scale="variable"/>
                <Property Name="SemiProductPrice" Type="Edm.Decimal" Nullable="false" Precision="15" Scale="variable"/>
                <Property Name="MaterialPrice" Type="Edm.Decimal" Nullable="false" Precision="15" Scale="variable"/>
                <Property Name="Total" Type="Edm.Decimal" Nullable="false" Precision="15" Scale="variable"/>
                <Property Name="SalesActual" Type="Edm.Decimal" Nullable="false" Precision="15" Scale="variable"/>
                <Property Name="Salesforcast" Type="Edm.Decimal" Nullable="false" Precision="15" Scale="variable"/>
                <Property Name="Currency" Type="Edm.String" Nullable="false" MaxLength="5"/>
            </EntityType>
            <EntityContainer Name="Container">
                <EntitySet Name="ZC_DAYSTOCKTRANS" EntityType="com.sap.gateway.srvd.zui_daystocktrans_o4.v0001.ZC_DAYSTOCKTRANSType"/>
            </EntityContainer>
            <Annotations Target="SAP__self.ZC_DAYSTOCKTRANSType/ExcuDate">
                <Annotation Term="SAP__common.Label" String="日付"/>
            </Annotations>
            <Annotations Target="SAP__self.ZC_DAYSTOCKTRANSType/Companycode">
                <Annotation Term="SAP__common.Label" String="会社コード"/>
                <Annotation Term="SAP__common.ValueListReferences">
                    <Collection>
                        <String>../../../../srvd_f4/sap/i_companycodestdvh/0001;ps='srvd-zui_daystocktrans_o4-0001';va='com.sap.gateway.srvd.zui_daystocktrans_o4.v0001.et-zc_daystocktrans.companycode'/$metadata</String>
                    </Collection>
                </Annotation>
                <Annotation Term="SAP__common.FilterDefaultValue" String="1100"/>
            </Annotations>
            <Annotations Target="SAP__self.ZC_DAYSTOCKTRANSType/Plant">
                <Annotation Term="SAP__common.Label" String="プラント"/>
                <Annotation Term="SAP__common.ValueListReferences">
                    <Collection>
                        <String>../../../../srvd_f4/sap/i_plantstdvh/0001;ps='srvd-zui_daystocktrans_o4-0001';va='com.sap.gateway.srvd.zui_daystocktrans_o4.v0001.et-zc_daystocktrans.plant'/$metadata</String>
                    </Collection>
                </Annotation>
            </Annotations>
            <Annotations Target="SAP__self.ZC_DAYSTOCKTRANSType/BusinessPartner">
                <Annotation Term="SAP__common.Label" String="得意先BPコード"/>
                <Annotation Term="SAP__common.ValueListReferences">
                    <Collection>
                        <String>../../../../srvd_f4/sap/i_customer_vh/0001;ps='srvd-zui_daystocktrans_o4-0001';va='com.sap.gateway.srvd.zui_daystocktrans_o4.v0001.et-zc_daystocktrans.businesspartner'/$metadata</String>
                    </Collection>
                </Annotation>
            </Annotations>
            <Annotations Target="SAP__self.ZC_DAYSTOCKTRANSType/ProductPrice">
                <Annotation Term="SAP__measures.ISOCurrency" Path="Currency"/>
            </Annotations>
            <Annotations Target="SAP__self.ZC_DAYSTOCKTRANSType/SemiProductPrice">
                <Annotation Term="SAP__measures.ISOCurrency" Path="Currency"/>
            </Annotations>
            <Annotations Target="SAP__self.ZC_DAYSTOCKTRANSType/MaterialPrice">
                <Annotation Term="SAP__measures.ISOCurrency" Path="Currency"/>
            </Annotations>
            <Annotations Target="SAP__self.ZC_DAYSTOCKTRANSType/Total">
                <Annotation Term="SAP__measures.ISOCurrency" Path="Currency"/>
            </Annotations>
            <Annotations Target="SAP__self.ZC_DAYSTOCKTRANSType/SalesActual">
                <Annotation Term="SAP__measures.ISOCurrency" Path="Currency"/>
            </Annotations>
            <Annotations Target="SAP__self.ZC_DAYSTOCKTRANSType/Salesforcast">
                <Annotation Term="SAP__measures.ISOCurrency" Path="Currency"/>
            </Annotations>
            <Annotations Target="SAP__self.ZC_DAYSTOCKTRANSType/Currency">
                <Annotation Term="SAP__common.IsCurrency"/>
                <Annotation Term="SAP__common.IsUpperCase"/>
                <Annotation Term="SAP__common.Label" String="Document Currency"/>
                <Annotation Term="SAP__common.Heading" String="Crcy"/>
                <Annotation Term="SAP__common.QuickInfo" String="SD Document Currency"/>
            </Annotations>
            <Annotations Target="SAP__self.ZC_DAYSTOCKTRANSType">
                <Annotation Term="SAP__common.Label" String="Query CDS"/>
                <Annotation Term="SAP__UI.HeaderInfo">
                    <Record>
                        <PropertyValue Property="TypeName" String="Items"/>
                        <PropertyValue Property="TypeNamePlural" String="Items"/>
                    </Record>
                </Annotation>
                <Annotation Term="SAP__UI.LineItem">
                    <Collection>
                        <Record Type="SAP__UI.DataField">
                            <PropertyValue Property="Label" String="日付"/>
                            <PropertyValue Property="Value" Path="ExcuDate"/>
                        </Record>
                        <Record Type="SAP__UI.DataField">
                            <PropertyValue Property="Label" String="会社コード"/>
                            <PropertyValue Property="Value" Path="Companycode"/>
                        </Record>
                        <Record Type="SAP__UI.DataField">
                            <PropertyValue Property="Label" String="プラント"/>
                            <PropertyValue Property="Value" Path="Plant"/>
                        </Record>
                        <Record Type="SAP__UI.DataField">
                            <PropertyValue Property="Label" String="得意先BPコード"/>
                            <PropertyValue Property="Value" Path="BusinessPartner"/>
                        </Record>
                        <Record Type="SAP__UI.DataField">
                            <PropertyValue Property="Label" String="得意先名"/>
                            <PropertyValue Property="Value" Path="BusinessPartnerName"/>
                        </Record>
                        <Record Type="SAP__UI.DataField">
                            <PropertyValue Property="Label" String="製品"/>
                            <PropertyValue Property="Value" Path="ProductPrice"/>
                        </Record>
                        <Record Type="SAP__UI.DataField">
                            <PropertyValue Property="Label" String="半製品"/>
                            <PropertyValue Property="Value" Path="SemiProductPrice"/>
                        </Record>
                        <Record Type="SAP__UI.DataField">
                            <PropertyValue Property="Label" String="原材料"/>
                            <PropertyValue Property="Value" Path="MaterialPrice"/>
                        </Record>
                        <Record Type="SAP__UI.DataField">
                            <PropertyValue Property="Label" String="合計"/>
                            <PropertyValue Property="Value" Path="Total"/>
                        </Record>
                        <Record Type="SAP__UI.DataField">
                            <PropertyValue Property="Label" String="売上実績（先月）"/>
                            <PropertyValue Property="Value" Path="SalesActual"/>
                        </Record>
                        <Record Type="SAP__UI.DataField">
                            <PropertyValue Property="Label" String="売上予測（翌月）"/>
                            <PropertyValue Property="Value" Path="Salesforcast"/>
                        </Record>
                        <Record Type="SAP__UI.DataField">
                            <PropertyValue Property="Label" String="通貨"/>
                            <PropertyValue Property="Value" Path="Currency"/>
                        </Record>
                    </Collection>
                </Annotation>
                <Annotation Term="SAP__UI.SelectionFields">
                    <Collection>
                        <PropertyPath>ExcuDate</PropertyPath>
                        <PropertyPath>Companycode</PropertyPath>
                        <PropertyPath>Plant</PropertyPath>
                        <PropertyPath>BusinessPartner</PropertyPath>
                    </Collection>
                </Annotation>
            </Annotations>
            <Annotations Target="SAP__self.Container/ZC_DAYSTOCKTRANS">
                <Annotation Term="SAP__capabilities.SearchRestrictions">
                    <Record>
                        <PropertyValue Property="Searchable" Bool="false"/>
                    </Record>
                </Annotation>
                <Annotation Term="SAP__capabilities.FilterRestrictions">
                    <Record>
                        <PropertyValue Property="Filterable" Bool="true"/>
                        <PropertyValue Property="FilterExpressionRestrictions">
                            <Collection>
                                <Record>
                                    <PropertyValue Property="Property" PropertyPath="ExcuDate"/>
                                    <PropertyValue Property="AllowedExpressions" String="SingleValue"/>
                                </Record>
                                <Record>
                                    <PropertyValue Property="Property" PropertyPath="Companycode"/>
                                    <PropertyValue Property="AllowedExpressions" String="SingleValue"/>
                                </Record>
                            </Collection>
                        </PropertyValue>
                        <PropertyValue Property="RequiredProperties">
                            <Collection>
                                <PropertyPath>ExcuDate</PropertyPath>
                            </Collection>
                        </PropertyValue>
                    </Record>
                </Annotation>
                <Annotation Term="SAP__capabilities.InsertRestrictions">
                    <Record>
                        <PropertyValue Property="Insertable" Bool="false"/>
                    </Record>
                </Annotation>
                <Annotation Term="SAP__capabilities.DeleteRestrictions">
                    <Record>
                        <PropertyValue Property="Deletable" Bool="false"/>
                    </Record>
                </Annotation>
                <Annotation Term="SAP__capabilities.UpdateRestrictions">
                    <Record>
                        <PropertyValue Property="Updatable" Bool="false"/>
                        <PropertyValue Property="QueryOptions">
                            <Record>
                                <PropertyValue Property="SelectSupported" Bool="true"/>
                            </Record>
                        </PropertyValue>
                    </Record>
                </Annotation>
                <Annotation Term="SAP__core.OptimisticConcurrency">
                    <Collection/>
                </Annotation>
            </Annotations>
            <Annotations Target="SAP__self.Container">
                <Annotation Term="SAP__CodeList.CurrencyCodes">
                    <Record>
                        <PropertyValue Property="Url" String="../../../../default/iwbep/common/0001/$metadata"/>
                        <PropertyValue Property="CollectionPath" String="Currencies"/>
                    </Record>
                </Annotation>
                <Annotation Term="SAP__aggregation.ApplySupported">
                    <Record>
                        <PropertyValue Property="Transformations">
                            <Collection>
                                <String>aggregate</String>
                                <String>groupby</String>
                                <String>filter</String>
                            </Collection>
                        </PropertyValue>
                        <PropertyValue Property="Rollup" EnumMember="SAP__aggregation.RollupType/None"/>
                    </Record>
                </Annotation>
                <Annotation Term="SAP__common.ApplyMultiUnitBehaviorForSortingAndFiltering" Bool="true"/>
                <Annotation Term="SAP__capabilities.FilterFunctions">
                    <Collection>
                        <String>eq</String>
                        <String>ne</String>
                        <String>gt</String>
                        <String>ge</String>
                        <String>lt</String>
                        <String>le</String>
                        <String>and</String>
                        <String>or</String>
                        <String>contains</String>
                        <String>startswith</String>
                        <String>endswith</String>
                        <String>any</String>
                        <String>all</String>
                    </Collection>
                </Annotation>
                <Annotation Term="SAP__capabilities.SupportedFormats">
                    <Collection>
                        <String>application/json</String>
                        <String>application/pdf</String>
                    </Collection>
                </Annotation>
                <Annotation Term="SAP__PDF.Features">
                    <Record>
                        <PropertyValue Property="DocumentDescriptionReference" String="../../../../default/iwbep/common/0001/$metadata"/>
                        <PropertyValue Property="DocumentDescriptionCollection" String="MyDocumentDescriptions"/>
                        <PropertyValue Property="ArchiveFormat" Bool="true"/>
                        <PropertyValue Property="Border" Bool="true"/>
                        <PropertyValue Property="CoverPage" Bool="true"/>
                        <PropertyValue Property="FitToPage" Bool="true"/>
                        <PropertyValue Property="FontName" Bool="true"/>
                        <PropertyValue Property="FontSize" Bool="true"/>
                        <PropertyValue Property="Margin" Bool="true"/>
                        <PropertyValue Property="Padding" Bool="true"/>
                        <PropertyValue Property="Signature" Bool="true"/>
                        <PropertyValue Property="HeaderFooter" Bool="true"/>
                        <PropertyValue Property="ResultSizeDefault" Int="20000"/>
                        <PropertyValue Property="ResultSizeMaximum" Int="20000"/>
                        <PropertyValue Property="IANATimezoneFormat" Bool="true"/>
                        <PropertyValue Property="Treeview" Bool="true"/>
                    </Record>
                </Annotation>
                <Annotation Term="SAP__capabilities.KeyAsSegmentSupported"/>
                <Annotation Term="SAP__capabilities.AsynchronousRequestsSupported"/>
            </Annotations>
        </Schema>
    </edmx:DataServices>
</edmx:Edmx>